mobius_mpd/__init__.py
mobius_mpd/albumentations_transform.py
mobius_mpd/torch_transform.py
mobius_mpd-0.1.6.dist-info/licenses/LICENSE
mobius_mpd-0.1.6.dist-info/METADATA
mobius_mpd-0.1.6.dist-info/WHEEL
mobius_mpd-0.1.6.dist-info/top_level.txt
mobius_mpd-0.1.6.dist-info/RECORD
