Metadata-Version: 2.4
Name: mobius-mpd
Version: 0.1.6
Summary: Möbius Perspective Distortion (MPD) data‑augmentation transform.
Author-email: Prakash Chandra Chhipa <prakash.chandra.chhipa@gmail.com>
Project-URL: Homepage, https://github.com/prakashchhipa/mobius-mpd
Project-URL: ParentProject, https://prakashchhipa.github.io/projects/mpd/
Project-URL: Paper, https://arxiv.org/abs/2405.02296
Keywords: data‑augmentation,vision,perspective‑distortion,albumentations,torchvision
Requires-Python: >=3.8
License-File: LICENSE
Requires-Dist: torch>=1.12
Requires-Dist: torchvision>=0.13
Requires-Dist: albumentations>=1.0.3
Requires-Dist: numpy
Requires-Dist: Pillow
Dynamic: license-file
